dsd_elections
