Metadata-Version: 1.0
Name: dsd-elections
Version: 0.2.0
Summary: Scrape and package election data from Wikipedia.
Home-page: UNKNOWN
Author: Robin Linderborg
Author-email: robin@datastory.org
License: UNKNOWN
Platform: UNKNOWN
